pycls/__init__.py
pycls/core/__init__.py
pycls/core/benchmark.py
pycls/core/builders.py
pycls/core/checkpoint.py
pycls/core/config.py
pycls/core/distributed.py
pycls/core/io.py
pycls/core/logging.py
pycls/core/meters.py
pycls/core/net.py
pycls/core/optimizer.py
pycls/core/plotting.py
pycls/core/timer.py
pycls/core/trainer.py
pycls/datasets/__init__.py
pycls/datasets/cifar10.py
pycls/datasets/imagenet.py
pycls/datasets/loader.py
pycls/datasets/transforms.py
pycls/models/__init__.py
pycls/models/anynet.py
pycls/models/effnet.py
pycls/models/model_zoo.py
pycls/models/regnet.py
pycls/models/resnet.py
pycls-0.1.1.dist-info/LICENSE
pycls-0.1.1.dist-info/METADATA
pycls-0.1.1.dist-info/WHEEL
pycls-0.1.1.dist-info/top_level.txt
pycls-0.1.1.dist-info/RECORD
