Metadata-Version: 2.1
Name: pycls
Version: 0.1.1
Summary: A codebase for image classification
Home-page: https://github.com/facebookresearch/pycls
License: UNKNOWN
Platform: UNKNOWN
Classifier: Programming Language :: Python :: 3
Classifier: License :: OSI Approved :: MIT License
Requires-Dist: numpy
Requires-Dist: opencv-python
Requires-Dist: simplejson
Requires-Dist: yacs
